Metadata-Version: 2.1
Name: ussd-airflow-engine
Version: 0.0.8
Summary: Ussd Airflow Library
Home-page: https://github.com/ussd-airflow/ussd_engine
Author: Mwas
Author-email: mwasgize@gmail.com
Maintainer: mwas
License: MIT
Platform: UNKNOWN
